{"assets":[],"v":"4.1.7","ddd":0,"layers":[{"ddd":0,"ind":0,"ty":4,"nm":"Shape Layer 1","ks":{"o":{"k":100},"r":{"k":0},"p":{"k":[300,300,0]},"a":{"k":[0,0,0]},"s":{"k":[100,100,100]}},"hasMask":true,"masksProperties":[{"cl":true,"inv":false,"mode":"a","pt":{"k":[{"i":{"x":0.833,"y":0.833},"o":{"x":0.167,"y":0.167},"n":"0p833_0p833_0p167_0p167","t":0,"s":[{"i":[[0,0],[0,0],[0,0],[0,0]],"o":[[0,0],[0,0],[0,0],[0,0]],"v":[[-276,-245],[-201,111.355],[-208.645,-140.645],[30.355,-120]]}],"e":[{"i":[[0,0],[0,0],[0,0],[0,0]],"o":[[0,0],[0,0],[0,0],[0,0]],"v":[[-276,-245],[-253,177.355],[147.355,192.355],[64.355,-153]]}]},{"t":72}]},"o":{"k":[{"i":{"x":[0.833],"y":[0.833]},"o":{"x":[0.167],"y":[0.167]},"n":["0p833_0p833_0p167_0p167"],"t":0,"s":[0],"e":[100]},{"t":30}]},"x":{"k":0},"nm":"Mask 1"},{"cl":true,"inv":false,"mode":"a","pt":{"k":{"i":[[0,0],[0,0],[0,0],[0,0]],"o":[[0,0],[0,0],[0,0],[0,0]],"v":[[-152,-76],[-149,49.355],[-47.645,42.355],[-46.645,-72]]}},"o":{"k":100},"x":{"k":0},"nm":"Mask 2"}],"shapes":[{"ty":"gr","it":[{"ty":"rc","d":1,"s":{"k":[231.355,231.355]},"p":{"k":[0,0]},"r":{"k":20},"nm":"Rectangle Path 1","closed":true},{"ty":"st","fillEnabled":true,"c":{"k":[255,255,255,255]},"o":{"k":100},"w":{"k":2},"lc":1,"lj":1,"ml":4,"nm":"Stroke 1"},{"ty":"fl","fillEnabled":true,"c":{"k":[255,255,255,255]},"o":{"k":100},"nm":"Fill 1"},{"ty":"tr","p":{"k":[-85.322,-4.322]},"a":{"k":[0,0]},"s":{"k":[100,100]},"r":{"k":0},"o":{"k":100},"sk":{"k":0},"sa":{"k":0}}],"nm":"Rectangle 1"}],"bounds":{"l":-277,"t":-196,"b":187,"r":106},"ip":0,"op":180,"st":0}],"ip":0,"op":180,"fr":60,"w":600,"h":600}