{"assets":[],"v":"4.1.7","ddd":0,"layers":[{"ddd":0,"ind":0,"ty":4,"nm":"Shape Layer 1","ks":{"o":{"k":100},"r":{"k":0},"p":{"k":[194.412,346.511,0]},"a":{"k":[0,0,0]},"s":{"k":[100,100,100]}},"hasMask":true,"masksProperties":[{"cl":true,"inv":false,"mode":"n","pt":{"k":{"i":[[0,0],[0,0],[0,0],[0,0]],"o":[[0,0],[0,0],[0,0],[0,0]],"v":[[-58.718,-217.552],[-256.718,83.954],[206.314,295.954],[386.314,-21.552]]}},"o":{"k":100},"x":{"k":0},"nm":"Mask 1"}],"shapes":[{"ty":"gr","it":[{"ind":0,"ty":"sh","closed":true,"ks":{"k":{"i":[[0,0],[0,0],[0,0],[0,0]],"o":[[0,0],[0,0],[0,0],[0,0]],"v":[[-202,-166],[-276,-34],[-94,84],[24,-14]]}},"nm":"Path 1"},{"ty":"st","fillEnabled":true,"c":{"k":[255,255,255,255]},"o":{"k":100},"w":{"k":[{"i":{"x":[0.833],"y":[0.833]},"o":{"x":[0.167],"y":[0.167]},"n":["0p833_0p833_0p167_0p167"],"t":1,"s":[2],"e":[42],"__fnct":[null]},{"i":{"x":[0.833],"y":[0.833]},"o":{"x":[0.167],"y":[0.167]},"n":["0p833_0p833_0p167_0p167"],"t":49,"s":[42],"e":[4],"__fnct":[null]},{"t":94}]},"lc":1,"lj":1,"ml":4,"nm":"Stroke 1"},{"ty":"fl","fillEnabled":true,"c":{"k":[255,0,0,255]},"o":{"k":[{"i":{"x":[0.833],"y":[0.833]},"o":{"x":[0.167],"y":[0.167]},"n":["0p833_0p833_0p167_0p167"],"t":25,"s":[100],"e":[5]},{"i":{"x":[0.833],"y":[0.833]},"o":{"x":[0.167],"y":[0.167]},"n":["0p833_0p833_0p167_0p167"],"t":59,"s":[5],"e":[95]},{"t":95}]},"nm":"Fill 1"},{"ty":"tr","p":{"k":[{"i":{"x":0.833,"y":0.833},"o":{"x":0.167,"y":0.167},"n":"0p833_0p833_0p167_0p167","t":0,"s":[321.912,-198.699],"e":[462.037,-79.761],"to":[23.3541660308838,19.8229160308838],"ti":[-22.5794277191162,-38.458984375]},{"i":{"x":0.833,"y":0.833},"o":{"x":0.167,"y":0.167},"n":"0p833_0p833_0p167_0p167","t":48,"s":[462.037,-79.761],"e":[457.388,32.055],"to":[22.5794277191162,38.458984375],"ti":[0.77473956346512,-18.6360683441162]},{"t":86}]},"a":{"k":[0,0]},"s":{"k":[100,100]},"r":{"k":0},"o":{"k":100},"sk":{"k":0},"sa":{"k":0}}],"nm":"Shape 1"},{"ty":"gr","it":[{"ty":"gr","it":[{"ind":0,"ty":"sh","closed":true,"ks":{"k":{"i":[[19,26],[24,-49],[-12,-23],[-37,-19],[-21,13]],"o":[[-19,-26],[-24,49],[12,23],[37,19],[21,-13]],"v":[[118,22],[37,77],[32,134],[102,97],[145,136]]}},"nm":"Path 1"},{"ty":"st","fillEnabled":true,"c":{"k":[255,255,255,255]},"o":{"k":100},"w":{"k":2},"lc":1,"lj":1,"ml":4,"nm":"Stroke 1"},{"ty":"fl","fillEnabled":true,"c":{"k":[255,0,0,255]},"o":{"k":100},"nm":"Fill 1"},{"ty":"tr","p":{"k":[0,0]},"a":{"k":[0,0]},"s":{"k":[100,100]},"r":{"k":0},"o":{"k":100},"sk":{"k":0},"sa":{"k":0}}],"nm":"Shape 2"},{"ty":"gr","it":[{"ind":0,"ty":"sh","closed":true,"ks":{"k":[{"i":{"x":0.833,"y":0.833},"o":{"x":0.167,"y":0.167},"n":"0p833_0p833_0p167_0p167","t":10,"s":[{"i":[[18,-10],[-42,-71],[-14,4],[-18,6],[0,24]],"o":[[-18,10],[42,71],[14,-4],[18,-6],[0,-24]],"v":[[-176,-176],[-170,-78],[-144,-118],[-99,-74],[-98,-141]]}],"e":[{"i":[[18,-10],[-34.371,74.991],[-14,4],[-18,6],[0,24]],"o":[[-18,10],[26.174,-57.108],[14,-4],[18,-6],[0,-24]],"v":[[-216,-111],[-170,-78],[-83,-128],[-27,-165],[-128,-173]]}]},{"i":{"x":0.833,"y":0.833},"o":{"x":0.167,"y":0.167},"n":"0p833_0p833_0p167_0p167","t":57,"s":[{"i":[[18,-10],[-34.371,74.991],[-14,4],[-18,6],[0,24]],"o":[[-18,10],[26.174,-57.108],[14,-4],[18,-6],[0,-24]],"v":[[-216,-111],[-170,-78],[-83,-128],[-27,-165],[-128,-173]]}],"e":[{"i":[[18,-10],[-21.916,-79.528],[-2.018,-14.42],[-18,6],[0,24]],"o":[[-18,10],[3.738,13.566],[2.738,19.566],[18,-6],[0,-24]],"v":[[-152,-212],[-117,-135],[-95,-109],[-84,-81],[-68,-166]]}]},{"t":102}]},"nm":"Path 1"},{"ty":"st","fillEnabled":true,"c":{"k":[255,255,255,255]},"o":{"k":100},"w":{"k":2},"lc":1,"lj":1,"ml":4,"nm":"Stroke 1"},{"ty":"fl","fillEnabled":true,"c":{"k":[{"i":{"x":[0.833],"y":[0.833]},"o":{"x":[0.167],"y":[0.167]},"n":["0p833_0p833_0p167_0p167"],"t":0,"s":[255,0,0,255],"e":[255,235,144,255]},{"i":{"x":[0.833],"y":[0.833]},"o":{"x":[0.167],"y":[0.167]},"n":["0p833_0p833_0p167_0p167"],"t":43,"s":[255,235,144,255],"e":[255,255,255,255]},{"i":{"x":[0.833],"y":[0.833]},"o":{"x":[0.167],"y":[0.167]},"n":["0p833_0p833_0p167_0p167"],"t":68,"s":[255,255,255,255],"e":[80,113,254,255]},{"i":{"x":[0.833],"y":[0.833]},"o":{"x":[0.167],"y":[0.167]},"n":["0p833_0p833_0p167_0p167"],"t":90,"s":[80,113,254,255],"e":[23,24,114,255]},{"t":104}]},"o":{"k":100},"nm":"Fill 1"},{"ty":"tr","p":{"k":[{"i":{"x":0.833,"y":0.833},"o":{"x":0.167,"y":0.167},"n":"0p833_0p833_0p167_0p167","t":0,"s":[0,0],"e":[142.406,207.922],"to":[23.734375,34.6536445617676],"ti":[-43.421875,7.0078125]},{"i":{"x":0.833,"y":0.833},"o":{"x":0.167,"y":0.167},"n":"0p833_0p833_0p167_0p167","t":29,"s":[142.406,207.922],"e":[260.531,-42.047],"to":[43.421875,-7.0078125],"ti":[-19.6875,41.6614570617676]},{"t":67}]},"a":{"k":[105,120]},"s":{"k":[100,100]},"r":{"k":0},"o":{"k":100},"sk":{"k":0},"sa":{"k":0}}],"nm":"Shape 1"},{"ty":"tr","p":{"k":[{"i":{"x":0.833,"y":0.833},"o":{"x":0.167,"y":0.167},"n":"0p833_0p833_0p167_0p167","t":0,"s":[-72.202,71.201],"e":[27.798,-57.799],"to":[16.6666660308838,-21.5],"ti":[-25.6666660308838,-1]},{"i":{"x":0.833,"y":0.833},"o":{"x":0.167,"y":0.167},"n":"0p833_0p833_0p167_0p167","t":50,"s":[27.798,-57.799],"e":[81.798,77.201],"to":[25.6666660308838,1],"ti":[-9,-22.5]},{"t":110}]},"a":{"k":[-74.202,-79.799]},"s":{"k":[100,100]},"r":{"k":0},"o":{"k":100},"sk":{"k":0},"sa":{"k":0}}],"nm":"Group 1"}],"bounds":{"l":-322,"t":-386,"b":318,"r":508},"ip":0,"op":180,"st":0}],"ip":0,"op":180,"fr":60,"w":600,"h":600}